{"assets/drawables/background.jpg":["assets/drawables/background.jpg"],"assets/drawables/background2.jpg":["assets/drawables/background2.jpg"],"assets/drawables/background3.jpg":["assets/drawables/background3.jpg"],"assets/drawables/background4.jpg":["assets/drawables/background4.jpg"],"assets/drawables/brand.png":["assets/drawables/brand.png"],"assets/drawables/cardBack1.png":["assets/drawables/cardBack1.png"],"assets/drawables/cardBack2.png":["assets/drawables/cardBack2.png"],"assets/drawables/cardBack3.png":["assets/drawables/cardBack3.png"],"assets/drawables/cardBack4.png":["assets/drawables/cardBack4.png"],"assets/drawables/card_score.png":["assets/drawables/card_score.png"],"assets/drawables/clubs.png":["assets/drawables/clubs.png"],"assets/drawables/clubs1.png":["assets/drawables/clubs1.png"],"assets/drawables/diamonds.png":["assets/drawables/diamonds.png"],"assets/drawables/diamonds1.png":["assets/drawables/diamonds1.png"],"assets/drawables/hearts.png":["assets/drawables/hearts.png"],"assets/drawables/hearts1.png":["assets/drawables/hearts1.png"],"assets/drawables/logo.png":["assets/drawables/logo.png"],"assets/drawables/spades.png":["assets/drawables/spades.png"],"assets/drawables/spades1.png":["assets/drawables/spades1.png"],"assets/drawables/taj.png":["assets/drawables/taj.png"],"assets/fonts/Vazirmatn-Bold.ttf":["assets/fonts/Vazirmatn-Bold.ttf"],"assets/fonts/Vazirmatn-Regular.ttf":["assets/fonts/Vazirmatn-Regular.ttf"],"assets/images/acec.png":["assets/images/acec.png"],"assets/images/aced.png":["assets/images/aced.png"],"assets/images/aceh.png":["assets/images/aceh.png"],"assets/images/aces.png":["assets/images/aces.png"],"assets/images/card_back_black.png":["assets/images/card_back_black.png"],"assets/images/card_back_blue.png":["assets/images/card_back_blue.png"],"assets/images/card_back_green.png":["assets/images/card_back_green.png"],"assets/images/card_back_purple.png":["assets/images/card_back_purple.png"],"assets/images/card_back_red.png":["assets/images/card_back_red.png"],"assets/images/eightc.png":["assets/images/eightc.png"],"assets/images/eightd.png":["assets/images/eightd.png"],"assets/images/eighth.png":["assets/images/eighth.png"],"assets/images/eights.png":["assets/images/eights.png"],"assets/images/fivec.png":["assets/images/fivec.png"],"assets/images/fived.png":["assets/images/fived.png"],"assets/images/fiveh.png":["assets/images/fiveh.png"],"assets/images/fives.png":["assets/images/fives.png"],"assets/images/fourc.png":["assets/images/fourc.png"],"assets/images/fourd.png":["assets/images/fourd.png"],"assets/images/fourh.png":["assets/images/fourh.png"],"assets/images/fours.png":["assets/images/fours.png"],"assets/images/jackc.png":["assets/images/jackc.png"],"assets/images/jackd.png":["assets/images/jackd.png"],"assets/images/jackh.png":["assets/images/jackh.png"],"assets/images/jacks.png":["assets/images/jacks.png"],"assets/images/kingc.png":["assets/images/kingc.png"],"assets/images/kingd.png":["assets/images/kingd.png"],"assets/images/kingh.png":["assets/images/kingh.png"],"assets/images/kings.png":["assets/images/kings.png"],"assets/images/ninec.png":["assets/images/ninec.png"],"assets/images/nined.png":["assets/images/nined.png"],"assets/images/nineh.png":["assets/images/nineh.png"],"assets/images/nines.png":["assets/images/nines.png"],"assets/images/queenc.png":["assets/images/queenc.png"],"assets/images/queend.png":["assets/images/queend.png"],"assets/images/queenh.png":["assets/images/queenh.png"],"assets/images/queens.png":["assets/images/queens.png"],"assets/images/sevenc.png":["assets/images/sevenc.png"],"assets/images/sevend.png":["assets/images/sevend.png"],"assets/images/sevenh.png":["assets/images/sevenh.png"],"assets/images/sevens.png":["assets/images/sevens.png"],"assets/images/sixc.png":["assets/images/sixc.png"],"assets/images/sixd.png":["assets/images/sixd.png"],"assets/images/sixh.png":["assets/images/sixh.png"],"assets/images/sixs.png":["assets/images/sixs.png"],"assets/images/table.png":["assets/images/table.png"],"assets/images/tenc.png":["assets/images/tenc.png"],"assets/images/tend.png":["assets/images/tend.png"],"assets/images/tenh.png":["assets/images/tenh.png"],"assets/images/tens.png":["assets/images/tens.png"],"assets/images/threec.png":["assets/images/threec.png"],"assets/images/threed.png":["assets/images/threed.png"],"assets/images/threeh.png":["assets/images/threeh.png"],"assets/images/threes.png":["assets/images/threes.png"],"assets/images/twoc.png":["assets/images/twoc.png"],"assets/images/twod.png":["assets/images/twod.png"],"assets/images/twoh.png":["assets/images/twoh.png"],"assets/images/twos.png":["assets/images/twos.png"],"assets/songs/boresh.mp3":["assets/songs/boresh.mp3"],"assets/songs/cardslide1.wav":["assets/songs/cardslide1.wav"],"assets/songs/deal.wav":["assets/songs/deal.wav"],"assets/songs/pakhsh.mp3":["assets/songs/pakhsh.mp3"],"assets/songs/select.wav":["assets/songs/select.wav"],"packages/cupertino_icons/assets/CupertinoIcons.ttf":["packages/cupertino_icons/assets/CupertinoIcons.ttf"]}